multi_validator/__init__.py
multi_validator/version.py
multi_validator/validator/__init__.py
multi_validator/validator/email.py
multi_validator/validator/network.py
multi_validator/validator/password.py
multi_validator/validator/person.py
multi_validator/validator/phone.py
multi_validator/validator/text.py
multi_validator-0.10.dist-info/LICENSE
multi_validator-0.10.dist-info/METADATA
multi_validator-0.10.dist-info/WHEEL
multi_validator-0.10.dist-info/top_level.txt
multi_validator-0.10.dist-info/RECORD
