Metadata-Version: 2.1
Name: multi-validator
Version: 0.10
Summary: This will validate multiple data type, i.e. phone number, email, name, age, weight, etc
Home-page: UNKNOWN
Author: Neel Ratan Guria
Author-email: UNKNOWN
License: UNKNOWN
Platform: UNKNOWN
